dir_manager/__init__.py
dir_manager/dir_manager.py
dir_manager-0.0.2.dist-info/METADATA
dir_manager-0.0.2.dist-info/WHEEL
dir_manager-0.0.2.dist-info/top_level.txt
dir_manager-0.0.2.dist-info/RECORD
