Metadata-Version: 2.1
Name: dir-manager
Version: 0.0.2
Summary: simple-dir-manager
Home-page: https://github.com/alkaline2018/dir-manager
Author: Song Seung Hwan
Author-email: shdth117@gmail.com
Classifier: Programming Language :: Python :: 3
Classifier: License :: OSI Approved :: MIT License
Classifier: Operating System :: OS Independent
Requires-Python: >=3.6
